opensim/__init__.py
opensim/__main__.py
opensim/run.py
opensim/modules/__init__.py
opensim/modules/arguments.py
opensim/modules/helper.py
opensim/modules/ngsi.py
opensim/modules/output.py
opensim/modules/sensor_things.py
oscsim/__init__.py
oscsim/__main__.py
oscsim/run.py
oscsim/modules/__init__.py
oscsim/modules/arguments.py
oscsim/modules/helper.py
oscsim/modules/ngsi.py
oscsim/modules/output.py
oscsim/modules/sensor_things.py
oscsim-1.1.2.dist-info/LICENSE
oscsim-1.1.2.dist-info/METADATA
oscsim-1.1.2.dist-info/WHEEL
oscsim-1.1.2.dist-info/entry_points.txt
oscsim-1.1.2.dist-info/top_level.txt
oscsim-1.1.2.dist-info/RECORD
