Metadata-Version: 2.1
Name: oscsim
Version: 1.1.2
Summary: Open Smart City-Sim is a lightweight tool to send test data to an Orion Context Broker or FROST-Server respectively.
Home-page: https://github.com/HYPERTEGRITY-AG/OpenSim
Author: Will Freitag
Author-email: Wilhelm.Freitag@omp.de
License: MIT License
Project-URL: Bug Tracker, https://github.com/HYPERTEGRITY-AG/OpenSim/projects/1
Platform: UNKNOWN
Classifier: Development Status :: 5 - Production/Stable
Classifier: Environment :: Console
Classifier: Intended Audience :: End Users/Desktop
Classifier: Intended Audience :: Developers
Classifier: Intended Audience :: System Administrators
Classifier: Programming Language :: Python :: 3
Classifier: License :: OSI Approved :: MIT License
Classifier: Operating System :: OS Independent
Requires-Python: >=3.6
License-File: LICENSE
Requires-Dist: requests (>=2.22.0)
Requires-Dist: paho-mqtt (>=1.5.1)
